primoseip/__init__.py
primoseip-0.2.dist-info/LICENSE
primoseip-0.2.dist-info/METADATA
primoseip-0.2.dist-info/WHEEL
primoseip-0.2.dist-info/top_level.txt
primoseip-0.2.dist-info/RECORD
