Metadata-Version: 2.1
Name: primoseip
Version: 0.2
Summary: Practica 4 de la asignatura fundamentos de Python
Home-page: UNKNOWN
Author: David Garcia Reche
Author-email: dreche@embarba.com
License: GNU GPLv3
Keywords: practica clase 4 EIP
Platform: UNKNOWN
Classifier: Development Status :: 4 - Beta
Classifier: Environment :: Console
Classifier: Intended Audience :: Developers
Classifier: Topic :: Utilities
Classifier: License :: OSI Approved :: GNU General Public License v3 (GPLv3)
Classifier: Programming Language :: Python :: 3
Classifier: Operating System :: OS Independent
